pyjsonpatch/__init__.py
pyjsonpatch/apply.py
pyjsonpatch/generate.py
pyjsonpatch/types.py
pyjsonpatch/utils.py
pyjsonpatch-0.1.3.dist-info/METADATA
pyjsonpatch-0.1.3.dist-info/WHEEL
pyjsonpatch-0.1.3.dist-info/licenses/LICENSE
pyjsonpatch-0.1.3.dist-info/RECORD
